finbright_futures/__init__.py
finbright_futures/binance.py
finbright_futures/data_collector.py
finbright_futures/definitions.py
finbright_futures/api/__init__.py
finbright_futures/api/constant/__init__.py
finbright_futures/api/constant/account_type.py
finbright_futures/api/constant/interval.py
finbright_futures/api/constant/margin_mode.py
finbright_futures/api/constant/order_side.py
finbright_futures/api/constant/order_status.py
finbright_futures/api/constant/order_type.py
finbright_futures/api/constant/position_mode.py
finbright_futures/api/constant/position_side.py
finbright_futures/api/constant/symbols.csv
finbright_futures/api/constant/time_in_force.py
finbright_futures/api/exchange/__init__.py
finbright_futures/api/exchange/binance/__init__.py
finbright_futures/api/exchange/binance/binance.py
finbright_futures/api/exchange/binance/future.py
finbright_futures/api/exchange/binance/request.py
finbright_futures/api/exchange/binance/wallet.py
finbright_futures/api/interface/__init__.py
finbright_futures/api/interface/exchange.py
finbright_futures/api/interface/future.py
finbright_futures/api/interface/request.py
finbright_futures/api/interface/spot.py
finbright_futures/api/interface/wallet.py
finbright_futures/api/model/__init__.py
finbright_futures/api/model/balance.py
finbright_futures/api/model/buy_sell_ratio.py
finbright_futures/api/model/candle.py
finbright_futures/api/model/daily_ticker_price_change.py
finbright_futures/api/model/deposit_address.py
finbright_futures/api/model/long_short_ratio.py
finbright_futures/api/model/network_info.py
finbright_futures/api/model/open_interest.py
finbright_futures/api/model/open_interest_statistic.py
finbright_futures/api/model/order.py
finbright_futures/api/model/order_book.py
finbright_futures/api/model/order_book_row.py
finbright_futures/api/model/order_book_ticker.py
finbright_futures/api/model/position.py
finbright_futures/api/model/price_ticker.py
finbright_futures/api/model/symbol_info.py
finbright_futures-0.0.4.dist-info/METADATA
finbright_futures-0.0.4.dist-info/WHEEL
finbright_futures-0.0.4.dist-info/RECORD
